QNPy_Latte/ATTENTION.py
QNPy_Latte/Clustering_with_SOM.py
QNPy_Latte/DATASETCLASS.py
QNPy_Latte/LOSS_METRICS.py
QNPy_Latte/MODEL_ARCHITECTURE.py
QNPy_Latte/PREDICTION.py
QNPy_Latte/PREPROCESS.py
QNPy_Latte/SPLITTING_AND_TRAINING.py
QNPy_Latte/__init__.py
QNPy_Latte-0.1.0.post2.dist-info/LICENSE
QNPy_Latte-0.1.0.post2.dist-info/METADATA
QNPy_Latte-0.1.0.post2.dist-info/WHEEL
QNPy_Latte-0.1.0.post2.dist-info/top_level.txt
QNPy_Latte-0.1.0.post2.dist-info/RECORD
