Metadata-Version: 2.1
Name: QNPy_Latte
Version: 0.1.0.post2
Summary: Latent ATTEntive Neural Processes for Quasar Light Curves with parametric recovery
Home-page: https://github.com/rajuaman1/QNPy_Latte
Author: Aman Raju, Marina Pavlovic, Andjelka Kovacevic, Dragana Ilic, Iva Cvorovic-Hajdinjak
Author-email: "Aman N. Raju" <rajuaman@gmail.com>
License: MIT License
Project-URL: Homepage, https://github.com/rajuaman1/QNPy_Latte
Requires-Python: >=3.7
License-File: LICENSE
Requires-Dist: astropy>=5.3.4
Requires-Dist: cycler>=0.11.0
Requires-Dist: dill>=0.3.4
Requires-Dist: matplotlib>=3.5.2
Requires-Dist: MiniSom>=2.3.1
Requires-Dist: numpy>=1.21.5
Requires-Dist: pandas>=1.4.4
Requires-Dist: plotly>=5.9.0
Requires-Dist: scikit-learn>=1.0.2
Requires-Dist: scipy>=1.9.1
Requires-Dist: seaborn>=0.12.2
Requires-Dist: torch>=1.13.0
Requires-Dist: tqdm>=4.64.1
Requires-Dist: tslearn>=0.6.2
